ndata/__init__.py
ndata/preprocess.py
ndata/utils.py
ndata-0.1.4.dist-info/LICENSE
ndata-0.1.4.dist-info/METADATA
ndata-0.1.4.dist-info/WHEEL
ndata-0.1.4.dist-info/top_level.txt
ndata-0.1.4.dist-info/RECORD
