Metadata-Version: 2.1
Name: ndata
Version: 0.1.4
Summary: Automated Data Preprocessing Library
Author: Leandre Nash
Classifier: Programming Language :: Python :: 3
Classifier: License :: OSI Approved :: MIT License
Classifier: Operating System :: OS Independent
Requires-Python: >=3.6
License-File: LICENSE
Requires-Dist: numpy
Requires-Dist: pandas
Requires-Dist: scikit-learn
Requires-Dist: scipy
